manual/tlazy.py
manual/tpath.py
manual/tsplit.py
tests/test_inter.py
tests/test_lazy.py
tests/test_path.py
tests/test_split.py
trial/ltrial.py
tstring/__init__.py
tstring/cpath.py
tstring/interpolation.py
tstring/lazy.py
tstring/safe_split.py
tstring_util-2.1.dist-info/LICENSE
tstring_util-2.1.dist-info/METADATA
tstring_util-2.1.dist-info/WHEEL
tstring_util-2.1.dist-info/top_level.txt
tstring_util-2.1.dist-info/RECORD
