Metadata-Version: 2.1
Name: tstring-util
Version: 2.1
Summary: Utilities for tstring
Author: Gerard Weatherby
Author-email: gerardw@alum.mit.edu
License: MIT
Project-URL: Homepage, https://github.com/Gerardwx/tstring-util
Project-URL: Repository, https://github.com/Gerardwx/tstring-util
Project-URL: Issues, https://github.com/Gerardwx/tstring-util/issues
Project-URL: Changelog, https://github.com/Gerardwx/tstring-util/releases
Requires-Python: >=3.14
License-File: LICENSE
Provides-Extra: test
Requires-Dist: pytest; extra == "test"
